[ { "MSG_TYPE": "ADT", "MSG_TYPE_EXT": "ABS" },
  { "MSG_TYPE": "ADT", "MSG_TYPE_EXT": "ADT" },
  { "MSG_TYPE": "ADT", "MSG_TYPE_EXT": "MR" },
  { "MSG_TYPE": "CDA", "MSG_TYPE_EXT": "CDA" },
  { "MSG_TYPE": "CSV", "MSG_TYPE_EXT": "CSV" },
  { "MSG_TYPE": "DFT", "MSG_TYPE_EXT": "DFT" },
  { "MSG_TYPE": "LAB", "MSG_TYPE_EXT": "LAB" },
  { "MSG_TYPE": "MDM", "MSG_TYPE_EXT": "MDM" },
  { "MSG_TYPE": "MFN", "MSG_TYPE_EXT": "MFN" },
  { "MSG_TYPE": "ORM", "MSG_TYPE_EXT": "OEO" },
  { "MSG_TYPE": "ORM", "MSG_TYPE_EXT": "ORM" },
  { "MSG_TYPE": "ORU", "MSG_TYPE_EXT": "EDM" },
  { "MSG_TYPE": "ORU", "MSG_TYPE_EXT": "LAB" },
  { "MSG_TYPE": "ORU", "MSG_TYPE_EXT": "NUR" },
  { "MSG_TYPE": "ORU", "MSG_TYPE_EXT": "ORU" },
  { "MSG_TYPE": "ORU", "MSG_TYPE_EXT": "RAD" },
  { "MSG_TYPE": "PAT", "MSG_TYPE_EXT": "PAT" },
  { "MSG_TYPE": "PPR", "MSG_TYPE_EXT": "EPS" },
  { "MSG_TYPE": "RAS", "MSG_TYPE_EXT": "PHA" },
  { "MSG_TYPE": "RDE", "MSG_TYPE_EXT": "HMED" },
  { "MSG_TYPE": "RDE", "MSG_TYPE_EXT": "RDE" },
  { "MSG_TYPE": "SIU", "MSG_TYPE_EXT": "SCH" },
  { "MSG_TYPE": "SIU", "MSG_TYPE_EXT": "SIU" },
  { "MSG_TYPE": "VXU", "MSG_TYPE_EXT": "VXU" } ]